odata_server/__init__.py
odata_server/edm.py
odata_server/flask.py
odata_server/meta.py
odata_server/middleware.py
odata_server/settings.py
odata_server/data/odata.abnf
odata_server/utils/__init__.py
odata_server/utils/common.py
odata_server/utils/flask.py
odata_server/utils/http.py
odata_server/utils/json.py
odata_server/utils/mongo.py
odata_server/utils/parse.py
odata_server-1.0.0a27.dist-info/licenses/LICENSE.txt
odata_server-1.0.0a27.dist-info/METADATA
odata_server-1.0.0a27.dist-info/WHEEL
odata_server-1.0.0a27.dist-info/top_level.txt
odata_server-1.0.0a27.dist-info/RECORD
